[{"__type__":"cc.SpriteFrame","content":{"name":"default_sprite","texture":"6eBWFz0oVHPLIGQKf/9Thu","rect":[0,2,40,36],"offset":[0,0],"originalSize":[40,40]}},[{"__type__":"cc.Prefab","_name":"TestDynamicTexture","data":{"__id__":1},"asyncLoadAssets":null},{"__type__":"cc.Node","_name":"TestDynamicTexture","_children":[{"__id__":2}],"_components":[{"__type__":"3d4d7Wqw5VOlI2H5DpZDpIN","node":{"__id__":1},"sprite":{"__id__":3}}],"_prefab":{"__type__":"cc.PrefabInfo","root":{"__id__":1},"asset":{"__uuid__":"aaycrEtwxNKJWnbl082lU2"},"fileId":"25MSRs+HxEtZoj6Pw0j/ox"}},{"__type__":"cc.Node","_name":"sprite","_parent":{"__id__":1},"_components":[{"__id__":3}],"_prefab":{"__type__":"cc.PrefabInfo","root":{"__id__":1},"asset":{"__uuid__":"aaycrEtwxNKJWnbl082lU2"},"fileId":"a9i00j5zhC9qMY4hW/sKEk"},"_contentSize":{"__type__":"cc.Size","width":40,"height":36}},{"__type__":"cc.Sprite","node":{"__id__":2},"_spriteFrame":{"__uuid__":"8c20Sso/ZEn7NUfNSM+EBh"}}]]